[
{"product_name": "MEGAMAN LG2603.5v2-E14", "price": "4.90"},
{"product_name": "MEGAMAN LG2603.5v2-E27", "price": "4.90"},
{"product_name": "MEGAMAN LG2605.5-E14", "price": "5.90"},
{"product_name": "MEGAMAN LG7105.5-E27", "price": "5.90"},
{"product_name": "MEGAMAN LG8606-E27", "price": "5.90"},
{"product_name": "MEGAMAN LG7208-E27", "price": "6.90"},
{"product_name": "MEGAMAN LG9603CS-E14", "price": "7.60"},
{"product_name": "MEGAMAN ER3405DG-WFL", "price": "7.90"},
{"product_name": "MEGAMAN LC0403.5v2-E14", "price": "7.90"},
{"product_name": "MEGAMAN LG7209.5-E27", "price": "7.90"},
{"product_name": "MEGAMAN ER2405LN-FL", "price": "9.90"},
{"product_name": "MEGAMAN ER3406DG-WFL", "price": "10.90"},
{"product_name": "MEGAMAN LC1403CS-E14", "price": "10.90"},
{"product_name": "MEGAMAN LG6104.8CS-E27", "price": "11.90"},
{"product_name": "MEGAMAN LR4604.5DG-WFL", "price": "11.90"},
{"product_name": "MEGAMAN LR6305LN-WFL", "price": "11.90"},
{"product_name": "MEGAMAN F31217RC", "price": "12.50"},
{"product_name": "MEGAMAN LG8207-E27", "price": "12.90"},
{"product_name": "MEGAMAN LT0409.5-2FT T8 TUBE", "price": "12.90"},
{"product_name": "MEGAMAN EU0401.8-G4", "price": "13.90"},
{"product_name": "MEGAMAN LG5502.4-E14", "price": "13.90"},
{"product_name": "MEGAMAN EU0102-G4", "price": "14.90"},
{"product_name": "MEGAMAN LG7311-E27", "price": "14.90"},
{"product_name": "MEGAMAN LU0702", "price": "14.90"},
{"product_name": "MEGAMAN LG7414-E27", "price": "15.90"},
{"product_name": "MEGAMAN LR4307-SWFL", "price": "15.90"},
{"product_name": "MEGAMAN LD0208x1d-C350", "price": "16.70"},
{"product_name": "MEGAMAN LC0403.5d-E14", "price": "16.90"},
{"product_name": "MEGAMAN LG3111-E27", "price": "16.90"},
{"product_name": "MEGAMAN LG7207d-E27", "price": "16.90"},
{"product_name": "MEGAMAN LR4605.5dDG-WFL UDIM", "price": "17.90"},
{"product_name": "MEGAMAN LT0518 - 4FT T8 TUBE", "price": "18.90"},
{"product_name": "MEGAMAN LG2310.5d-E27", "price": "19.60"},
{"product_name": "MEGAMAN F11914PD+IP44", "price": "19.90"},
{"product_name": "MEGAMAN LED LR2906-WFL-E27-PAR20", "price": "19.90"},
{"product_name": "MEGAMAN LG7310.5d-E27 DIM", "price": "19.90"},
{"product_name": "MEGAMAN LR1506-35H-COOLWHITE", "price": "19.90"},
{"product_name": "MEGAMAN LC0703CS-E14", "price": "20.90"},
{"product_name": "MEGAMAN LC1503.2dCS-E14", "price": "21.90"},
{"product_name": "MEGAMAN LG2604w-E14", "price": "21.90"},
{"product_name": "MEGAMAN LR2205", "price": "21.90"},
{"product_name": "MEGAMAN LC0404wCS-E14", "price": "22.90"},
{"product_name": "MEGAMAN LR3010.5-WFL-E27-PAR30", "price": "23.90"},
{"product_name": "MEGAMAN LJ0408-R7s", "price": "24.90"},
{"product_name": "MEGAMAN LG7003dGD-E27 DIM", "price": "25.90"},
{"product_name": "MEGAMAN LG9809dCS-E27", "price": "25.90"},
{"product_name": "MEGAMAN LG4105.5CS-E27", "price": "26.90"},
{"product_name": "MEGAMAN LG6703GD-E27", "price": "26.90"},
{"product_name": "MEGAMAN LR3307", "price": "26.90"},
{"product_name": "MEGAMAN LG2207d-E27", "price": "27.90"},
{"product_name": "MEGAMAN LG6803GD-E27", "price": "27.90"},
{"product_name": "MEGAMAN LG7813d-E27 DIM", "price": "27.90"},
{"product_name": "MEGAMAN LG2509.5s-E27", "price": "28.90"},
{"product_name": "MEGAMAN LG4003.5dCS-E14", "price": "28.90"},
{"product_name": "MEGAMAN LR2008d_50H35D-COOLWHITE", "price": "29.00"},
{"product_name": "MALCOLM Adjustable Recessed Downlight PAR16 (FULL SET WITH BULB)", "price": "29.90"},
{"product_name": "MEGAMAN ER3207-50H", "price": "29.90"},
{"product_name": "MEGAMAN LC1106wCS-E14", "price": "29.90"},
{"product_name": "MEGAMAN LG6903GD-E27", "price": "29.90"},
{"product_name": "MEGAMAN LG6603dGD-E27", "price": "30.90"},
{"product_name": "MEGAMAN ER2304-20H36D", "price": "32.90"},
{"product_name": "MEGAMAN LG6303dGD-E27", "price": "32.90"},
{"product_name": "MEGAMAN LR3215.5-WFL-PAR38", "price": "32.90"},
{"product_name": "MEGAMAN LG6403dGD-E27", "price": "33.90"},
{"product_name": "MEGAMAN LS0107d-Brass-E27", "price": "34.90"},
{"product_name": "ZENIA Recessed Downlight F26100RC 7.5WATT 4INCH (2 Years ONSITE Warranty)", "price": "34.90"},
{"product_name": "MEGAMAN LG6503dGD-E27", "price": "35.90"},
{"product_name": "MEGAMAN LR4204.5-35H24D", "price": "36.90"},
{"product_name": "MEGAMAN LR5906dHR-75H35D-WARMWHITE", "price": "36.90"},
{"product_name": "MEGAMAN LR5907dHR-75H35D-COOLWHITE", "price": "36.90"},
{"product_name": "MEGAMAN F50500SM", "price": "37.00"},
{"product_name": "MEGAMAN ER1708d-50H24D", "price": "39.90"},
{"product_name": "MEGAMAN LT0523.5-4FT T8 TUBE", "price": "41.90"},
{"product_name": "ZENIA Recessed Downlight F26200RC 12.5WATT 5INCH (2 Years ONSITE Warranty)", "price": "42.90"},
{"product_name": "MEGAMAN F50600SM", "price": "48.10"},
{"product_name": "MEGAMAN LG2311dBT-E27", "price": "49.90"},
{"product_name": "ZENIA Recessed Downlight F26400RC-D DIMMABLE 13WATT 3INCH (2 Years ONSITE Warranty)", "price": "49.90"},
{"product_name": "ZENIA Recessed Downlight F51400RC 12.5WATT 5INCH (2 Years ONSITE Warranty)", "price": "49.90"},
{"product_name": "ZENIA Recessed Downlight F54100RC 9.5WATT 5INCH (2 Years ONSITE Warranty)", "price": "49.90"},
{"product_name": "ZENIA Recessed Downlight F26300RC 20.5WATT 6INCH (2 Years ONSITE Warranty)", "price": "54.90"},
{"product_name": "ZENIA Recessed Downlight F26200RC-d 12.5WATT 5INCH DIMMABLE (2 Years ONSITE Warranty)", "price": "59.90"},
{"product_name": "MEGAMAN F50700SM", "price": "63.20"},
{"product_name": "MEGAMAN ER2711d-50H24D", "price": "65.90"},
{"product_name": "MEGAMAN ER2911d-50H45D", "price": "65.90"},
{"product_name": "ZENIA Recessed Downlight F27100RCV1 20.5 WATT 8INCH (2 Years ONSITE Warranty)", "price": "69.90"},
{"product_name": "MEGAMAN F03500SP", "price": "75.00"},
{"product_name": "ZENIA Recessed Downlight F27100RC 35.5 WATT 8INCH (2 Years ONSITE Warranty)", "price": "79.90"},
{"product_name": "MEGAMAN ER2912d-75H45D", "price": "83.90"},
{"product_name": "MEGAMAN LR1815d-75H45D", "price": "88.30"},
{"product_name": "MEGAMAN LR1615d-75H24D", "price": "88.90"},
{"product_name": "MEGAMAN LH0127-E27", "price": "109.90"},
{"product_name": "MEGAMAN LR1412d-75H30D-PAR30", "price": "119.90"},
{"product_name": "MEGAMAN F27000PL", "price": "122.00"},
{"product_name": "MEGAMAN LR0215d-100H24D-PAR30", "price": "129.90"},
{"product_name": "MEGAMAN F51100SM", "price": "145.20"},
{"product_name": "MEGAMAN F51300SM", "price": "145.20"},
{"product_name": "MEGAMAN F50100SM", "price": "146.00"},
{"product_name": "MEGAMAN LH0133-E27", "price": "146.90"},
{"product_name": "MEGAMAN LH0135-E27", "price": "146.90"},
{"product_name": "MEGAMAN LR0920-25M25D-PAR38", "price": "166.90"},
{"product_name": "MEGAMAN MH0130 + LB2601", "price": "178.90"},
{"product_name": "MEGAMAN F25600SM+IP54 2800k WARMWHITE", "price": "208.20"}
]